Metadata-Version: 2.1
Name: whirlcalc
Version: 2.1
Summary: Install Compie instead...
Home-page: https://github.com/Whirlpool-Programmer/whirlcalc
Author: Whirlpool-Programmer
Author-email: whirlpool.programmer@outlook.com
License: MIT License
Platform: UNKNOWN
Classifier: Programming Language :: Python :: 2
Classifier: Programming Language :: Python :: 3
Classifier: License :: OSI Approved :: MIT License
Classifier: Operating System :: OS Independent
License-File: LICENSE
